maxware_tsp_cli/__init__.py
maxware_tsp_cli/__main__.py
maxware_tsp_cli/cli.py
maxware_tsp_cli/cli_common.py
maxware_tsp_cli/commands/__init__.py
maxware_tsp_cli/commands/bootstrap.py
maxware_tsp_cli/commands/config.py
maxware_tsp_cli/commands/db/__init__.py
maxware_tsp_cli/commands/db/cli.py
maxware_tsp_cli/commands/db/connection.py
maxware_tsp_cli/commands/db/passwords.py
maxware_tsp_cli/commands/launch.py
maxware_tsp_cli/commands/rpc/__init__.py
maxware_tsp_cli/commands/rpc/cli.py
maxware_tsp_cli/commands/rpc/importer.py
maxware_tsp_cli/commands/rpc/modules.py
maxware_tsp_cli/commands/rpc/translations.py
maxware_tsp_cli/commands/shell.py
maxware_tsp_cli/commands/source_get.py
maxware_tsp_cli/commands/test.py
maxware_tsp_cli/git/__init__.py
maxware_tsp_cli/git/git_odoo.py
maxware_tsp_cli/git/git_odoo_addons.py
maxware_tsp_cli/git/git_repo.py
maxware_tsp_cli/git/git_url.py
maxware_tsp_cli/git/zip_download.py
maxware_tsp_cli/helpers/__init__.py
maxware_tsp_cli/helpers/bootstrap.py
maxware_tsp_cli/helpers/cli.py
maxware_tsp_cli/helpers/odoo_files.py
maxware_tsp_cli/helpers/odoo_manifest.py
maxware_tsp_cli/helpers/system.py
maxware_tsp_cli/version.py
maxware_tsp_cli-0.3.0.dist-info/LICENSE
maxware_tsp_cli-0.3.0.dist-info/METADATA
maxware_tsp_cli-0.3.0.dist-info/WHEEL
maxware_tsp_cli-0.3.0.dist-info/entry_points.txt
maxware_tsp_cli-0.3.0.dist-info/RECORD
