Metadata-Version: 2.1
Name: maxware-tsp-cli
Version: 0.3.0
Summary: 
Keywords: odoo,cli,maxware,tsp,godoo,rpc
Author: Abderrahim Guennoune
Author-email: aguennoune@outlook.com
Requires-Python: >=3.8.1,<3.12
Classifier: Programming Language :: Python :: 3
Classifier: Programming Language :: Python :: 3.9
Classifier: Programming Language :: Python :: 3.10
Classifier: Programming Language :: Python :: 3.11
Provides-Extra: codequality
Provides-Extra: devcontainer
Requires-Dist: gitpython (>=3.1.27,<4.0.0)
Requires-Dist: godoo-rpc (>=0.1.1,<0.2.0)
Requires-Dist: openupgradelib (>=3.3.4,<4.0.0)
Requires-Dist: passlib (>=1.7.3,<2.0.0)
Requires-Dist: psycopg2 (>=2.9.6,<3.0.0)
Requires-Dist: python-dotenv (>=0.20.0,<0.21.0)
Requires-Dist: ruamel-yaml (>=0.17.21,<0.18.0)
Requires-Dist: typer-common-functions (>=0.0.3,<0.0.4)
